grokcore.catalog-4.1-py3.12-nspkg.pth
grokcore/catalog/__init__.py
grokcore/catalog/components.py
grokcore/catalog/configure.zcml
grokcore/catalog/ftesting.zcml
grokcore/catalog/index.py
grokcore/catalog/interfaces.py
grokcore/catalog/meta.py
grokcore/catalog/meta.zcml
grokcore/catalog/testing.py
grokcore/catalog/tests/__init__.py
grokcore/catalog/tests/test_base.py
grokcore/catalog/tests/test_functional.py
grokcore/catalog/tests/base/__init__.py
grokcore/catalog/tests/base/catalog/__init__.py
grokcore/catalog/tests/base/catalog/indexes_module.py
grokcore/catalog/tests/base/catalog/indexes_no_app.py
grokcore/catalog/tests/functional/__init__.py
grokcore/catalog/tests/functional/catalog/__init__.py
grokcore/catalog/tests/functional/catalog/catalog.py
grokcore/catalog/tests/functional/catalog/indexes.py
grokcore/catalog/tests/functional/catalog/indexes_app_interface.py
grokcore/catalog/tests/functional/catalog/indexes_attribute.py
grokcore/catalog/tests/functional/catalog/indexes_class.py
grokcore/catalog/tests/functional/catalog/indexes_datetimeindex.py
grokcore/catalog/tests/functional/catalog/indexes_install_on.py
grokcore/catalog/tests/functional/catalog/indexes_multiple.py
grokcore/catalog/tests/functional/catalog/indexes_multiple_conflict.py
grokcore/catalog/tests/functional/catalog/indexes_name.py
grokcore/catalog/tests/functional/catalog/indexes_nonexistent.py
grokcore/catalog/tests/functional/catalog/indexes_set.py
grokcore/catalog/tests/functional/catalog/indexes_site.py
grokcore/catalog/tests/functional/catalog/indexes_valueindex.py
grokcore/catalog/tests/functional/catalog/setuporder.py
grokcore_catalog-4.1.dist-info/LICENSE.txt
grokcore_catalog-4.1.dist-info/METADATA
grokcore_catalog-4.1.dist-info/WHEEL
grokcore_catalog-4.1.dist-info/namespace_packages.txt
grokcore_catalog-4.1.dist-info/top_level.txt
grokcore_catalog-4.1.dist-info/RECORD
