Metadata-Version: 2.2
Name: grokcore.catalog
Version: 4.1
Summary: Grok-like configuration for catalog and indexes
Home-page: https://github.com/zopefoundation/grokcore.catalog
Author: Grok Team
Author-email: zope-dev@zope.dev
License: ZPL-2.1
Classifier: Environment :: Web Environment
Classifier: Intended Audience :: Developers
Classifier: License :: OSI Approved :: Zope Public License
Classifier: Programming Language :: Python
Classifier: Programming Language :: Python :: 3
Classifier: Programming Language :: Python :: 3.9
Classifier: Programming Language :: Python :: 3.10
Classifier: Programming Language :: Python :: 3.11
Classifier: Programming Language :: Python :: 3.12
Classifier: Programming Language :: Python :: 3.13
Classifier: Programming Language :: Python :: Implementation
Classifier: Programming Language :: Python :: Implementation :: CPython
Classifier: Programming Language :: Python :: Implementation :: PyPy
Classifier: Framework :: Zope :: 3
Requires-Python: >=3.9
License-File: LICENSE.txt
Requires-Dist: grokcore.component>=2.5
Requires-Dist: grokcore.site>=1.7
Requires-Dist: martian>=0.13
Requires-Dist: setuptools
Requires-Dist: zc.catalog
Requires-Dist: zope.annotation
Requires-Dist: zope.catalog
Requires-Dist: zope.component
Requires-Dist: zope.container
Requires-Dist: zope.event
Requires-Dist: zope.exceptions
Requires-Dist: zope.interface
Requires-Dist: zope.intid
Requires-Dist: zope.lifecycleevent
Requires-Dist: zope.keyreference
Requires-Dist: zope.site
Provides-Extra: test
Requires-Dist: grokcore.content; extra == "test"
Requires-Dist: zope.app.appsetup; extra == "test"
Requires-Dist: zope.component; extra == "test"
Requires-Dist: zope.configuration; extra == "test"
Requires-Dist: zope.location; extra == "test"
Requires-Dist: zope.testing; extra == "test"
Requires-Dist: zope.app.wsgi; extra == "test"
Dynamic: author
Dynamic: author-email
Dynamic: classifier
Dynamic: description
Dynamic: home-page
Dynamic: license
Dynamic: provides-extra
Dynamic: requires-dist
Dynamic: requires-python
Dynamic: summary
